{
  "PushToRemoteBranch": [
    "--username",
    "--remote-branch"
  ],
  "DisplayBuildOutputForBuildwebBuilds": [
    "--include-in-progress",
    "--log-line-count"
  ],
  "AppendTextToFile": [
    "--input-text",
    "--source-file"
  ],
  "ExitIfGitDiffDoesNotMatchRbtDiff": [
    "--parent"
  ],
  "GenerateReviewStats": [
    "--file-count-ranges",
    "--groups"
  ],
  "InvokeJenkinsJobs": [
    "--build-display-name",
    "--jenkins-jobs",
    "--wait-time",
    "--wait-for-action",
    "--ignore-jenkins-job-failure",
    "--job-display-names"
  ],
  "SyncChangelist": [
    "--tracking-branch",
    "--sync-to-branch-latest"
  ],
  "AddGitChangesToChangelist": [
    "--tracking-branch"
  ],
  "InvokeSandboxBuild": [
    "--use-git-tracking-branch",
    "--buildweb-branch",
    "--build-display-name",
    "--component-builds",
    "--build-type",
    "--buildweb-project",
    "--exclude-sync-to",
    "--store-trees",
    "--changelist-id"
  ],
  "SaveFileData": [
    "--destination-file"
  ],
  "AuthenticateAllApis": [
    "--bugzilla-test-bug",
    "--username"
  ],
  "AbortJenkinsBuilds": [
    "--jenkins-jobs"
  ],
  "LoadFileData": [
    "--source-file"
  ],
  "LoadReviewPatch": [
    "--username",
    "--latest-diff",
    "--review-request-id"
  ],
  "BaseCommitReadAction": [
    "--set-empty-only"
  ],
  "DisplayBuildOutputForJenkinsJobs": [
    "--include-in-progress",
    "--log-line-count"
  ],
  "UpdateReviewDetails": [
    "--tracking-branch",
    "--groups",
    "--disable-markdown"
  ],
  "CreateReviewIfNeeded": [
    "--username",
    "--review-board-repo"
  ],
  "UpdateTaskEstimates": [
    "--username",
    "--estimate"
  ],
  "RsyncCommand": [
    "--rsync-destination",
    "--rsync-flags",
    "--rsync-delete",
    "--rsync-source"
  ],
  "BaseBatchJiraAction": [
    "--username",
    "--disable-jira"
  ],
  "BaseSshAction": [
    "--ssh-password",
    "--ssh-username",
    "--ssh-port",
    "--ssh-host",
    "--ssh-site",
    "--use-database-host"
  ],
  "TailLogFile": [
    "--log-file",
    "--log-line-count",
    "--ssh-command",
    "--tail-follow"
  ],
  "BaseCommitUsingGitlabAction": [
    "--tracking-branch",
    "--target-merge-branch",
    "--username",
    "--source-merge-branch"
  ],
  "SyncChangelistWithGitDiff": [
    "--tracking-branch",
    "--sync-to-branch-latest"
  ],
  "ReadGitDiffAsGitPatch": [
    "--parent"
  ],
  "ExecuteLocalSqlStatementUsingPsql": [
    "--database-username",
    "--database-schema-name",
    "--sql-statement"
  ],
  "PublishReview": [
    "--publish-description",
    "--publish-as-trivial"
  ],
  "SelectVapp": [
    "--username",
    "--vapp-name",
    "--job-artifact",
    "--job-build-number",
    "--vapp-json-file"
  ],
  "LoadVapps": [
    "--username",
    "--vapp-json-file"
  ],
  "SetDefaultApprover": [
    "--approver"
  ],
  "SetJsonProperty": [
    "--property-value",
    "--json-property-path"
  ],
  "SaveDiffToFile": [
    "--output-file"
  ],
  "BaseCommitWithBuildwebBuildsAction": [
    "--username",
    "--buildweb-log-file-name",
    "--buildweb-api-url"
  ],
  "WaitForJenkinsBuildsToComplete": [
    "--wait-time"
  ],
  "DeleteJsonProperty": [
    "--json-property-path"
  ],
  "UploadReviewDiff": [
    "--tracking-branch",
    "--parent"
  ],
  "BaseCommitWithJenkinsBuildsAction": [
    "--username"
  ],
  "BaseBatchBugzillaAction": [
    "--username",
    "--default-jira-component",
    "--disable-bugzilla"
  ],
  "RenameVapp": [
    "--username",
    "--wait-time"
  ],
  "SetSummary": [
    "--set-empty-only"
  ],
  "WaitForBuildwebBuildsToComplete": [
    "--wait-time"
  ],
  "DeleteVapp": [
    "--username",
    "--wait-time",
    "--wait-for-action"
  ],
  "MarkBugAsResolved": [
    "--username"
  ],
  "ExecuteSshCommand": [
    "--output-file",
    "--ssh-strict-host-checking",
    "--build-display-name",
    "--ssh-command"
  ],
  "LoadVappJson": [
    "--username"
  ],
  "DisplayAliasesForWorkflows": [
    "--output-file",
    "--workflow-alias",
    "--include-alias-autocomplete"
  ],
  "CreateReview": [
    "--username",
    "--review-board-repo"
  ],
  "SubmitToDepot": [
    "--tracking-branch"
  ],
  "PushToPrecommitBranch": [
    "--username"
  ],
  "BackupFile": [
    "--backup-name",
    "--destination-file",
    "--source-file",
    "--skip-backup"
  ],
  "LoadCompletedIssuesWithoutResolution": [
    "--username"
  ],
  "RemoveReviewUrl": [
    "--always-include-review-url"
  ],
  "PostApprovalRequest": [
    "--approver"
  ],
  "EnableDisableMergeTo": [
    "--disable-merge-to"
  ],
  "OpenSshShell": [
    "--ssh-strict-host-checking"
  ],
  "FindMatchingLines": [
    "--log-file",
    "--input-text",
    "--line-count-after",
    "--line-count-before",
    "--ssh-command"
  ],
  "GenerateAutoCompleteValues": [
    "--autocomplete-workflow"
  ],
  "ExitIfVcdVmQuotaExceeded": [
    "--vcd-vm-quota",
    "--use-vapp-json"
  ],
  "ReadCertsFromUrl": [
    "--source-url"
  ],
  "LoadGitPatchFile": [
    "--diff-file"
  ],
  "CheckStatusOfLatestBuilds": [
    "--username",
    "--jenkins-jobs"
  ],
  "BaseTransitionJiraIssue": [
    "--username",
    "--disable-jira"
  ],
  "OpenVcdProviderApp": [
    "--vcd-cell-index"
  ],
  "ResolveBugsWithResolvedTrackingIssues": [
    "--username",
    "--disable-jira"
  ],
  "SetReviewId": [
    "--username"
  ],
  "GenerateGitCommitStats": [
    "--author-emails",
    "--last-number-of-days",
    "--line-count-ranges",
    "--file-count-ranges"
  ],
  "OpenVcdTenantApp": [
    "--vcd-tenant"
  ],
  "LoadVappsIfNeeded": [
    "--use-vapp-json",
    "--vcd-check-quota"
  ],
  "DisplayConfig": [
    "--specific-properties"
  ],
  "CreatePostgresDatabaseFromFile": [
    "--database-username",
    "--database-schema-name",
    "--source-file"
  ],
  "LoadIssues": [
    "--use-epics",
    "--use-fix-version",
    "--use-label",
    "--include-estimated",
    "--include-sprint-stories",
    "--include-issue-types",
    "--include-all-issue-types"
  ],
  "SelectVappIfNeeded": [
    "--use-vapp-json"
  ],
  "SkipPipelineIfSet": [
    "--skip-pipeline"
  ],
  "BaseCommitAction": [
    "--username",
    "--changelist-id"
  ],
  "ScpFileFromRemote": [
    "--ssh-strict-host-checking",
    "--destination-file",
    "--source-file"
  ],
  "SetCommitDetailsFromReview": [
    "--username",
    "--review-request-id"
  ],
  "BaseCommitUsingReviewBoardAction": [
    "--username"
  ],
  "UpdateVappLease": [
    "--username",
    "--vapp-lease",
    "--wait-time"
  ],
  "LoadVappJsonIfNeeded": [
    "--use-vapp-json"
  ],
  "ExitIfPostgresDatabaseAlreadyExists": [
    "--database-schema-name"
  ],
  "ExitIfChangelistDoesNotMatchGitBranch": [
    "--tracking-branch",
    "--sync-to-branch-latest"
  ],
  "LoadPerforcePatchFile": [
    "--diff-file"
  ],
  "ApplyPatch": [
    "--action-after-failed-patch-check",
    "--patch-command",
    "--use-patch-command"
  ],
  "BaseSetReviewersList": [
    "--always-include-review-url"
  ],
  "ExecuteSqlStatement": [
    "--database-password",
    "--database-username",
    "--database-driver-class",
    "--database-driver-file",
    "--sql-statement",
    "--database-url-pattern",
    "--database-url"
  ],
  "UpdatePublicCerts": [
    "--vcd-sys-admin-password",
    "--vcd-sys-admin-username"
  ],
  "SyncCardsWithJiraIssues": [
    "--keep-missing-cards"
  ],
  "SetBugNumbers": [
    "--username",
    "--disable-bugzilla",
    "--disable-jira"
  ],
  "BaseReviewBoardAction": [
    "--username"
  ],
  "CreateTrelloBoardIfNeeded": [
    "--own-boards-only"
  ],
  "DiscardUnpublishedReviews": [
    "--username"
  ],
  "BaseBatchCloseReviews": [
    "--username"
  ],
  "ReplaceText": [
    "--replacement-text",
    "--input-text"
  ],
  "DumpPostgresqlDatabaseFromRemote": [
    "--ssh-password",
    "--ssh-username",
    "--ssh-port",
    "--ssh-host",
    "--destination-file",
    "--source-database-schema-name"
  ],
  "DownloadBuildArtifact": [
    "--job-with-artifact",
    "--job-build-number",
    "--destination-file",
    "--job-artifact"
  ],
  "SelectVcdCell": [
    "--vcd-cell-index"
  ],
  "SelectVcdSite": [
    "--vcd-site-index"
  ],
  "BaseSetUsersList": [
    "--search-by-usernames-only",
    "--username"
  ],
  "PushToTrackingBranch": [
    "--tracking-branch"
  ],
  "SetProperty": [
    "--property-name",
    "--property-value"
  ],
  "ComputeTestbedVmCountIfNeeded": [
    "--vcd-check-quota"
  ],
  "ReadPendingChangelist": [
    "--username",
    "--changelist-id"
  ]
}